README.md
setup.py
bin/frat
bin/frat_config
bin/frat_json2coco
bin/frat_json2png
bin/frat_json2yolov5
frat/__init__.py
frat/formats.py
frat/generic_web_server.py
frat/paths.py
frat/version.py
frat.egg-info/PKG-INFO
frat.egg-info/SOURCES.txt
frat.egg-info/dependency_links.txt
frat.egg-info/requires.txt
frat.egg-info/top_level.txt
frat/resources/empty_page.json
frat/resources/font_annotation_config.json
frat/resources/frat_gui.js
frat/resources/frat_webpage.jinja2
frat/resources/seals_annotation_config.json