Metadata-Version: 2.1
Name: frat
Version: 2.0.7
Summary: Fast Rectangle Annotation Tool
Home-page: https://github.com/anguelos/frat
Author: Anguelos Nicolaou
Author-email: anguelos.nicolaou@gmail.com
License: GPLv3
Keywords: documents,groudtruthing,webbased
Platform: UNKNOWN
Classifier: Intended Audience :: Science/Research
Classifier: Programming Language :: Python :: 3.6
Classifier: Programming Language :: Python :: 3.7
Classifier: Programming Language :: Python :: 3.8
Classifier: Topic :: Scientific/Engineering
